qrmagic/__init__.py
qrmagic/_version.py
qrmagic/api.py
qrmagic/labelmaker.py
qrmagic/scanimages.py
qrmagic-0.2.3.dist-info/LICENSE
qrmagic-0.2.3.dist-info/METADATA
qrmagic-0.2.3.dist-info/WHEEL
qrmagic-0.2.3.dist-info/entry_points.txt
qrmagic-0.2.3.dist-info/top_level.txt
qrmagic-0.2.3.dist-info/RECORD
