Metadata-Version: 2.1
Name: qrmagic
Version: 0.2.3
Summary: Tools to manage qrcoded labels and images during Natural Variaiton experiments
Author-email: kdm9 <foss@kdmurray.id.au>
Keywords: qrcode,fieldwork
Classifier: Programming Language :: Python
Classifier: Programming Language :: Python :: 3
Classifier: Development Status :: 3 - Alpha
Classifier: Environment :: Console
Classifier: Intended Audience :: Developers
Classifier: Operating System :: OS Independent
Classifier: Topic :: Software Development :: Libraries :: Python Modules
Classifier: Topic :: Scientific/Engineering :: Bio-Informatics
License-File: LICENSE
Requires-Dist: exifread
Requires-Dist: flask >=2.1
Requires-Dist: heif-image-plugin
Requires-Dist: pillow
Requires-Dist: piexif
Requires-Dist: pylabels
Requires-Dist: pyzbar
Requires-Dist: qrcode
Requires-Dist: reportlab
Requires-Dist: tqdm
Requires-Dist: whitenoise
